[
    {
        "my_db_data": {
            "description": "SPDR S&P 500 ETF TRUST",
            "symbol": "SPY",
            "isin": "US78462F1030",
            "position_id": 2192,
            "account_id": 85,
            "asset_id": 1432,
            "report_date": "2026-02-04",
            "quantity": 18.8606,
            "mark_price": 686.19,
            "position_value": 12941.96,
            "cost_basis_money": 10975.697922,
            "cost_basis_price": 581.937898158,
            "open_price": 581.937898158,
            "fifo_pnl_unrealized": 1966.262078,
            "percent_of_nav": 100.0,
            "side": "Long",
            "level_of_detail": "SUMMARY",
            "open_date_time": NaN,
            "vesting_date": NaN,
            "accrued_interest": NaN,
            "fx_rate_to_base": 1.0,
            "currency": "USD"
        },
        "ib_contract_details": {
            "official_name": "SS SPDR S&P 500 ETF TRUST-US",
            "industry": "",
            "category": "",
            "subcategory": "",
            "market_name": "SPY",
            "stock_type": "ETF",
            "contract_month": "",
            "min_tick": 0.01,
            "trading_hours": "20260206:0400-20260206:2000"
        },
        "ib_market_snapshot": {
            "market_price": 688.21,
            "close_price": 677.62,
            "bid": 688.2,
            "ask": 688.21,
            "volume": 45992360.0,
            "high_52week": 688.4,
            "low_52week": 680.85,
            "greeks": "N/A"
        },
        "ib_fundamental": "N/A"
    },
    {
        "my_db_data": {
            "description": "NVIDIA CORP",
            "symbol": "NVDA",
            "isin": "US67066G1040",
            "position_id": 2193,
            "account_id": 729,
            "asset_id": 1107,
            "report_date": "2026-02-04",
            "quantity": 1.0,
            "mark_price": 174.19,
            "position_value": 174.19,
            "cost_basis_money": 123.544892,
            "cost_basis_price": 123.544892,
            "open_price": 123.544892,
            "fifo_pnl_unrealized": 50.645108,
            "percent_of_nav": 1.92,
            "side": "Long",
            "level_of_detail": "SUMMARY",
            "open_date_time": NaN,
            "vesting_date": NaN,
            "accrued_interest": NaN,
            "fx_rate_to_base": 1.0,
            "currency": "USD"
        },
        "ib_contract_details": {
            "official_name": "NVIDIA CORP",
            "industry": "Technology",
            "category": "Semiconductors",
            "subcategory": "Electronic Compo-Semicon",
            "market_name": "NMS",
            "stock_type": "COMMON",
            "contract_month": "",
            "min_tick": 0.01,
            "trading_hours": "20260206:0400-20260206:2000"
        },
        "ib_market_snapshot": {
            "market_price": 184.33,
            "close_price": 171.88,
            "bid": 184.32,
            "ask": 184.33,
            "volume": 124712200.0,
            "high_52week": 184.51,
            "low_52week": 174.6,
            "greeks": "N/A"
        },
        "ib_fundamental": "N/A"
    },
    {
        "my_db_data": {
            "description": "BLACKROCK CAPITAL ALLOCATION",
            "symbol": "BCAT",
            "isin": "US09260U1097",
            "position_id": 2195,
            "account_id": 631,
            "asset_id": 307,
            "report_date": "2026-02-04",
            "quantity": 1712.0,
            "mark_price": 14.73,
            "position_value": 25217.76,
            "cost_basis_money": 25046.580468,
            "cost_basis_price": 14.630011956,
            "open_price": 14.630011956,
            "fifo_pnl_unrealized": 171.179532,
            "percent_of_nav": 10.4,
            "side": "Long",
            "level_of_detail": "SUMMARY",
            "open_date_time": NaN,
            "vesting_date": NaN,
            "accrued_interest": NaN,
            "fx_rate_to_base": 1.0,
            "currency": "USD"
        },
        "ib_contract_details": {
            "official_name": "BLACKROCK CAPITAL ALLOC TR",
            "industry": "",
            "category": "",
            "subcategory": "",
            "market_name": "BCAT",
            "stock_type": "CLOSED-END FUND",
            "contract_month": "",
            "min_tick": 0.01,
            "trading_hours": "20260206:0400-20260206:2000"
        },
        "ib_market_snapshot": {
            "market_price": 14.75,
            "close_price": 14.64,
            "bid": 14.74,
            "ask": 14.75,
            "volume": 358900.0,
            "high_52week": 14.77,
            "low_52week": 14.66,
            "greeks": "N/A"
        },
        "ib_fundamental": "N/A"
    },
    {
        "my_db_data": {
            "description": "BlackRock Core Bond Trust",
            "symbol": "BHK",
            "isin": "",
            "position_id": 2196,
            "account_id": 631,
            "asset_id": 316,
            "report_date": "2026-02-04",
            "quantity": 2050.0,
            "mark_price": 9.52,
            "position_value": 19516.0,
            "cost_basis_money": 19971.313371,
            "cost_basis_price": 9.742104083,
            "open_price": 9.742104083,
            "fifo_pnl_unrealized": -455.313371,
            "percent_of_nav": 8.05,
            "side": "Long",
            "level_of_detail": "SUMMARY",
            "open_date_time": NaN,
            "vesting_date": NaN,
            "accrued_interest": NaN,
            "fx_rate_to_base": 1.0,
            "currency": "USD"
        },
        "ib_contract_details": {
            "official_name": "BLACKROCK CORE BOND TRUST",
            "industry": "",
            "category": "",
            "subcategory": "",
            "market_name": "BHK",
            "stock_type": "CLOSED-END FUND",
            "contract_month": "",
            "min_tick": 0.01,
            "trading_hours": "20260206:0400-20260206:2000"
        },
        "ib_market_snapshot": {
            "market_price": 9.55,
            "close_price": 9.55,
            "bid": 9.54,
            "ask": 9.55,
            "volume": 91800.0,
            "high_52week": 9.58,
            "low_52week": 9.53,
            "greeks": "N/A"
        },
        "ib_fundamental": "N/A"
    },
    {
        "my_db_data": {
            "description": "DOUBLELINE INCOME SOLUTIONS",
            "symbol": "DSL",
            "isin": "",
            "position_id": 2197,
            "account_id": 631,
            "asset_id": 528,
            "report_date": "2026-02-04",
            "quantity": 1562.0,
            "mark_price": 11.49,
            "position_value": 17947.38,
            "cost_basis_money": 20023.524882,
            "cost_basis_price": 12.819158055,
            "open_price": 12.819158055,
            "fifo_pnl_unrealized": -2076.144882,
            "percent_of_nav": 7.4,
            "side": "Long",
            "level_of_detail": "SUMMARY",
            "open_date_time": NaN,
            "vesting_date": NaN,
            "accrued_interest": NaN,
            "fx_rate_to_base": 1.0,
            "currency": "USD"
        },
        "ib_contract_details": {
            "official_name": "DOUBLELINE INCOME SOLUTIONS",
            "industry": "",
            "category": "",
            "subcategory": "",
            "market_name": "DSL",
            "stock_type": "CLOSED-END FUND",
            "contract_month": "",
            "min_tick": 0.01,
            "trading_hours": "20260206:0400-20260206:2000"
        },
        "ib_market_snapshot": {
            "market_price": 11.47,
            "close_price": 11.43,
            "bid": 11.46,
            "ask": 11.47,
            "volume": 614600.0,
            "high_52week": 11.52,
            "low_52week": 11.44,
            "greeks": "N/A"
        },
        "ib_fundamental": "N/A"
    },
    {
        "my_db_data": {
            "description": "ALLSPRING INCOME OPPORTUNITI",
            "symbol": "EAD",
            "isin": "US94987B1052",
            "position_id": 2198,
            "account_id": 631,
            "asset_id": 534,
            "report_date": "2026-02-04",
            "quantity": 2846.0,
            "mark_price": 6.87,
            "position_value": 19552.02,
            "cost_basis_money": 19707.578434,
            "cost_basis_price": 6.924658621,
            "open_price": 6.924658621,
            "fifo_pnl_unrealized": -155.558434,
            "percent_of_nav": 8.06,
            "side": "Long",
            "level_of_detail": "SUMMARY",
            "open_date_time": NaN,
            "vesting_date": NaN,
            "accrued_interest": NaN,
            "fx_rate_to_base": 1.0,
            "currency": "USD"
        },
        "ib_contract_details": {
            "official_name": "ALLSPRING INCOME OPPORT",
            "industry": "",
            "category": "",
            "subcategory": "",
            "market_name": "EAD",
            "stock_type": "CLOSED-END FUND",
            "contract_month": "",
            "min_tick": 0.01,
            "trading_hours": "20260206:0400-20260206:2000"
        },
        "ib_market_snapshot": {
            "market_price": 6.84,
            "close_price": 6.85,
            "bid": 6.84,
            "ask": 6.85,
            "volume": 133900.0,
            "high_52week": 6.9,
            "low_52week": 6.84,
            "greeks": "N/A"
        },
        "ib_fundamental": "N/A"
    },
    {
        "my_db_data": {
            "description": "EATON VANCE TAX-MANAGED DIVE",
            "symbol": "ETY",
            "isin": "",
            "position_id": 2199,
            "account_id": 631,
            "asset_id": 560,
            "report_date": "2026-02-04",
            "quantity": 1300.0,
            "mark_price": 14.9,
            "position_value": 19370.0,
            "cost_basis_money": 19520.034544,
            "cost_basis_price": 15.015411188,
            "open_price": 15.015411188,
            "fifo_pnl_unrealized": -150.034544,
            "percent_of_nav": 7.99,
            "side": "Long",
            "level_of_detail": "SUMMARY",
            "open_date_time": NaN,
            "vesting_date": NaN,
            "accrued_interest": NaN,
            "fx_rate_to_base": 1.0,
            "currency": "USD"
        },
        "ib_contract_details": {
            "official_name": "EATON VANCE TAX-MGD DIV EQTY",
            "industry": "",
            "category": "",
            "subcategory": "",
            "market_name": "ETY",
            "stock_type": "CLOSED-END FUND",
            "contract_month": "",
            "min_tick": 0.01,
            "trading_hours": "20260206:0400-20260206:2000"
        },
        "ib_market_snapshot": {
            "market_price": 14.98,
            "close_price": 14.77,
            "bid": 14.98,
            "ask": 15.01,
            "volume": 97900.0,
            "high_52week": 15.01,
            "low_52week": 14.85,
            "greeks": "N/A"
        },
        "ib_fundamental": "N/A"
    }
]